tier/__init__.py
tier/py.typed
tier/tier.py
tier/types.py
tier_sdk-0.1.2.dist-info/METADATA
tier_sdk-0.1.2.dist-info/WHEEL
tier_sdk-0.1.2.dist-info/licenses/LICENSE.md
tier_sdk-0.1.2.dist-info/RECORD
